{
  "1": {
    "Name": "Legs",
    "ApproxTime": "1h",
    "Series": {
      "1": {
        "Name": "Squats",
        "NumberOfSets": "3",
        "TimeBetweenSets": "1min 30",
        "TimeAfterSets": "2min",
        "Exercise": {
          "Name": "Squat",
          "NumberOfRepetitions": "until failure",
          "PathToVideo": "",
          "PathToCoverImage": ""
        }
      },
      "2": {
        "Name": "Leg presses",
        "NumberOfSets": "3",
        "TimeBetweenSets": "1min 30",
        "TimeAfterSets": "2min",
        "Exercise": {
          "Name": "Leg press",
          "NumberOfRepetitions": "until failure",
          "PathToVideo": "",
          "PathToCoverImage": ""
        }
      }
    }
  }
}